nanobanana_mcp_server/__init__.py
nanobanana_mcp_server/server.py
nanobanana_mcp_server/config/__init__.py
nanobanana_mcp_server/config/constants.py
nanobanana_mcp_server/config/settings.py
nanobanana_mcp_server/core/__init__.py
nanobanana_mcp_server/core/exceptions.py
nanobanana_mcp_server/core/progress_tracker.py
nanobanana_mcp_server/core/server.py
nanobanana_mcp_server/core/validation.py
nanobanana_mcp_server/prompts/__init__.py
nanobanana_mcp_server/prompts/design.py
nanobanana_mcp_server/prompts/editing.py
nanobanana_mcp_server/prompts/photography.py
nanobanana_mcp_server/resources/__init__.py
nanobanana_mcp_server/resources/file_metadata.py
nanobanana_mcp_server/resources/operation_status.py
nanobanana_mcp_server/resources/stored_images.py
nanobanana_mcp_server/resources/template_catalog.py
nanobanana_mcp_server/services/__init__.py
nanobanana_mcp_server/services/enhanced_image_service.py
nanobanana_mcp_server/services/file_image_service.py
nanobanana_mcp_server/services/file_service.py
nanobanana_mcp_server/services/files_api_service.py
nanobanana_mcp_server/services/gemini_client.py
nanobanana_mcp_server/services/image_database_service.py
nanobanana_mcp_server/services/image_service.py
nanobanana_mcp_server/services/image_storage_service.py
nanobanana_mcp_server/services/maintenance_service.py
nanobanana_mcp_server/services/model_selector.py
nanobanana_mcp_server/services/pro_image_service.py
nanobanana_mcp_server/services/template_service.py
nanobanana_mcp_server/tools/__init__.py
nanobanana_mcp_server/tools/generate_image.py
nanobanana_mcp_server/tools/maintenance.py
nanobanana_mcp_server/tools/output_stats.py
nanobanana_mcp_server/tools/upload_file.py
nanobanana_mcp_server/utils/__init__.py
nanobanana_mcp_server/utils/image_utils.py
nanobanana_mcp_server/utils/logging_utils.py
nanobanana_mcp_server/utils/validation_utils.py
nanobanana_mcp_server-0.3.3.dist-info/METADATA
nanobanana_mcp_server-0.3.3.dist-info/WHEEL
nanobanana_mcp_server-0.3.3.dist-info/entry_points.txt
nanobanana_mcp_server-0.3.3.dist-info/licenses/LICENSE
nanobanana_mcp_server-0.3.3.dist-info/RECORD
