Metadata-Version: 2.4
Name: nanobanana-mcp-server
Version: 0.3.3
Summary: A production-ready MCP server for AI-powered image generation using Gemini 3 Pro Image (Nano Banana Pro) and Gemini 2.5 Flash Image with intelligent model selection
Project-URL: Homepage, https://github.com/nano-banana/mcp-server
Project-URL: Repository, https://github.com/nano-banana/mcp-server.git
Project-URL: Documentation, https://docs.nanobanana.dev
Project-URL: Bug Tracker, https://github.com/nano-banana/mcp-server/issues
Author-email: zhongwei <lizhongwei.nkcs@gmail.com>
License: MIT
License-File: LICENSE
Keywords: 4k,ai,fastmcp,gemini,grounding,image-generation,mcp,nano-banana-pro
Classifier: Development Status :: 3 - Alpha
Classifier: Intended Audience :: Developers
Classifier: License :: OSI Approved :: MIT License
Classifier: Programming Language :: Python :: 3
Classifier: Programming Language :: Python :: 3.11
Classifier: Programming Language :: Python :: 3.12
Classifier: Topic :: Multimedia :: Graphics
Classifier: Topic :: Scientific/Engineering :: Artificial Intelligence
Classifier: Topic :: Software Development :: Libraries :: Python Modules
Requires-Python: >=3.11
Requires-Dist: fastmcp>=2.11.0
Requires-Dist: google-genai>=1.57.0
Requires-Dist: pillow>=10.4.0
Requires-Dist: pydantic>=2.0.0
Requires-Dist: python-dotenv>=1.0.1
Provides-Extra: dev
Requires-Dist: black>=23.0.0; extra == 'dev'
Requires-Dist: fastmcp>=2.11.0; extra == 'dev'
Requires-Dist: isort>=5.12.0; extra == 'dev'
Requires-Dist: mypy>=1.0.0; extra == 'dev'
Requires-Dist: pre-commit>=3.0.0; extra == 'dev'
Requires-Dist: pytest-asyncio>=0.21.0; extra == 'dev'
Requires-Dist: pytest-cov>=4.0.0; extra == 'dev'
Requires-Dist: pytest>=7.0.0; extra == 'dev'
Requires-Dist: ruff>=0.1.0; extra == 'dev'
Provides-Extra: docs
Requires-Dist: mkdocs-material>=9.0.0; extra == 'docs'
Requires-Dist: mkdocs>=1.4.0; extra == 'docs'
Requires-Dist: mkdocstrings[python]>=0.20.0; extra == 'docs'
Provides-Extra: test
Requires-Dist: pytest-asyncio>=0.21.0; extra == 'test'
Requires-Dist: pytest-cov>=4.0.0; extra == 'test'
Requires-Dist: pytest-mock>=3.10.0; extra == 'test'
Requires-Dist: pytest>=7.0.0; extra == 'test'
Requires-Dist: responses>=0.23.0; extra == 'test'
